menu_select/Menu_select.py
menu_select/__init__.py
menu_select/core.py
menu_select/os_terminal_controller.py
menu_select/linux/__init__.py
menu_select/linux/key_dic.py
menu_select/linux/linux_terminal_controller.py
menu_select/windows/__init__.py
menu_select/windows/key_dic.py
menu_select/windows/windows_terminal_controller.py
tests/__init__.py
tests/test_menu_select.py
menu_select-1.0.3.dist-info/METADATA
menu_select-1.0.3.dist-info/WHEEL
menu_select-1.0.3.dist-info/top_level.txt
menu_select-1.0.3.dist-info/RECORD
