Metadata-Version: 2.4
Name: menu_select
Version: 1.0.3
Summary: Uma biblioteca para criação de menus seletivos
Home-page: https://github.com/VG-Correa/menu_select
Author: VG-Correa
Author-email: v.victorgabriel2014@gmail.com
Classifier: Programming Language :: Python :: 3
Classifier: License :: OSI Approved :: MIT License
Classifier: Operating System :: OS Independent
Requires-Python: >=3.13
Dynamic: author
Dynamic: author-email
Dynamic: classifier
Dynamic: description
Dynamic: description-content-type
Dynamic: home-page
Dynamic: requires-python
Dynamic: summary
